modoboa_imap_migration/__init__.py
modoboa_imap_migration/apps.py
modoboa_imap_migration/auth_backends.py
modoboa_imap_migration/checks.py
modoboa_imap_migration/factories.py
modoboa_imap_migration/forms.py
modoboa_imap_migration/handlers.py
modoboa_imap_migration/models.py
modoboa_imap_migration/modo_extension.py
modoboa_imap_migration/serializers.py
modoboa_imap_migration/settings.py
modoboa_imap_migration/tests.py
modoboa_imap_migration/urls.py
modoboa_imap_migration/urls_api.py
modoboa_imap_migration/views.py
modoboa_imap_migration/viewsets.py
modoboa_imap_migration/locale/cs_CZ/LC_MESSAGES/django.mo
modoboa_imap_migration/locale/cs_CZ/LC_MESSAGES/django.po
modoboa_imap_migration/locale/de/LC_MESSAGES/django.mo
modoboa_imap_migration/locale/de/LC_MESSAGES/django.po
modoboa_imap_migration/locale/el_GR/LC_MESSAGES/django.mo
modoboa_imap_migration/locale/el_GR/LC_MESSAGES/django.po
modoboa_imap_migration/locale/en/LC_MESSAGES/django.mo
modoboa_imap_migration/locale/en/LC_MESSAGES/django.po
modoboa_imap_migration/locale/fr/LC_MESSAGES/django.mo
modoboa_imap_migration/locale/fr/LC_MESSAGES/django.po
modoboa_imap_migration/locale/it/LC_MESSAGES/django.mo
modoboa_imap_migration/locale/it/LC_MESSAGES/django.po
modoboa_imap_migration/locale/ja_JP/LC_MESSAGES/django.mo
modoboa_imap_migration/locale/ja_JP/LC_MESSAGES/django.po
modoboa_imap_migration/locale/nl_NL/LC_MESSAGES/django.mo
modoboa_imap_migration/locale/nl_NL/LC_MESSAGES/django.po
modoboa_imap_migration/locale/pt_BR/LC_MESSAGES/django.mo
modoboa_imap_migration/locale/pt_BR/LC_MESSAGES/django.po
modoboa_imap_migration/locale/sl_SI/LC_MESSAGES/django.mo
modoboa_imap_migration/locale/sl_SI/LC_MESSAGES/django.po
modoboa_imap_migration/locale/sv/LC_MESSAGES/django.mo
modoboa_imap_migration/locale/sv/LC_MESSAGES/django.po
modoboa_imap_migration/management/__init__.py
modoboa_imap_migration/management/commands/__init__.py
modoboa_imap_migration/management/commands/generate_offlineimap_config.py
modoboa_imap_migration-1.4.1.dist-info/LICENSE
modoboa_imap_migration-1.4.1.dist-info/METADATA
modoboa_imap_migration-1.4.1.dist-info/WHEEL
modoboa_imap_migration-1.4.1.dist-info/top_level.txt
modoboa_imap_migration-1.4.1.dist-info/RECORD
